pcloudy_mcp/__init__.py
pcloudy_mcp/main.py
pcloudy_mcp/server.py
pcloudy_mcp/Constant/constant.py
pcloudy_mcp/api/app_management.py
pcloudy_mcp/api/authenticate.py
pcloudy_mcp/api/browser_booking.py
pcloudy_mcp/api/device_booking.py
pcloudy_mcp/api/http_client.py
pcloudy_mcp/api/qpilot.py
pcloudy_mcp/errors/exception.py
pcloudy_mcp/logger/logger.py
pcloudy_mcp/tools/__init__.py
pcloudy_mcp/tools/app_management.py
pcloudy_mcp/tools/browser_booking.py
pcloudy_mcp/tools/device_booking.py
pcloudy_mcp/tools/qpilot.py
pcloudy_mcp/utils/config.py
pcloudy_mcp/utils/token_cache.py
pcloudy_mcp/utils/tools_auto_registry.py
pcloudy_mcp/utils/tools_config.py
pcloudy_mcp/utils/tools_response_format.py
pcloudy_mcp/validation/validation.py
pcloudy_mcp-0.1.3.dist-info/METADATA
pcloudy_mcp-0.1.3.dist-info/WHEEL
pcloudy_mcp-0.1.3.dist-info/entry_points.txt
pcloudy_mcp-0.1.3.dist-info/RECORD
